aquosRemote/__init__.py
aquosRemote/aquos.py
aquosRemote-1.5.1.dist-info/LICENSE
aquosRemote-1.5.1.dist-info/METADATA
aquosRemote-1.5.1.dist-info/WHEEL
aquosRemote-1.5.1.dist-info/top_level.txt
aquosRemote-1.5.1.dist-info/RECORD
