Metadata-Version: 2.1
Name: aquosRemote
Version: 1.5.1
Summary: A small Python module for sending Remote Control Codes to your Sharp AQUOS Smart TV
Home-page: https://github.com/thehappydinoa/aquosRemote
Author: thehappydinoa
Author-email: thehappydinoa@gmail.com
License: MIT
Project-URL: Bug Reports, https://github.com/thehappydinoa/aquosRemote/issues
Project-URL: Say Thanks!, http://saythanks.io/to/thehappydinoa
Project-URL: Contribute!, https://github.com/thehappydinoa/aquosRemote/pulls
Project-URL: Follow Me!, https://twitter.com/thehappydinoa/
Keywords: aquos tv remote
Platform: UNKNOWN
Classifier: License :: OSI Approved :: MIT License
Classifier: Programming Language :: Python
Classifier: Programming Language :: Python :: 3
Classifier: Programming Language :: Python :: 3.5
Classifier: Programming Language :: Python :: 3.6
Classifier: Programming Language :: Python :: 3.7
Classifier: Programming Language :: Python :: Implementation :: PyPy
Requires-Python: >=3.5.0
Provides-Extra: dev
Requires-Dist: twine ; extra == 'dev'
Requires-Dist: unittest ; extra == 'dev'
